sqlupy-0.0.3.dist-info/METADATA
sqlupy-0.0.3.dist-info/WHEEL
sqlupy-0.0.3.dist-info/license_files/LICENSE
sqlupy/__init__.py
sqlupy/sqlupy.cp39-win_amd64.pyd
sqlupy-0.0.3.dist-info/RECORD
