Metadata-Version: 2.1
Name: sqlupy
Version: 0.0.3
Classifier: Programming Language :: Rust
Classifier: Programming Language :: Python :: Implementation :: CPython
Classifier: Programming Language :: Python :: Implementation :: PyPy
License-File: LICENSE
Requires-Python: >=3.7
